householdsim/__init__.py
householdsim/model.py
householdsim/mosaik.py
mosaik.HouseholdSim_SemVer-2.0.4rc20220724000607.dist-info/AUTHORS.txt
mosaik.HouseholdSim_SemVer-2.0.4rc20220724000607.dist-info/LICENSE.txt
mosaik.HouseholdSim_SemVer-2.0.4rc20220724000607.dist-info/METADATA
mosaik.HouseholdSim_SemVer-2.0.4rc20220724000607.dist-info/WHEEL
mosaik.HouseholdSim_SemVer-2.0.4rc20220724000607.dist-info/entry_points.txt
mosaik.HouseholdSim_SemVer-2.0.4rc20220724000607.dist-info/top_level.txt
mosaik.HouseholdSim_SemVer-2.0.4rc20220724000607.dist-info/RECORD
