Metadata-Version: 2.1
Name: mosaik.HouseholdSim-SemVer
Version: 2.0.4rc20220724000607
Summary: A simple simulator for household profiles.
Home-page: https://bitbucket.org/mosaik/mosaik-householdsim
Author: Stefan Scherfke
Author-email: mosaik@offis.de
Maintainer: Bengt Lüers
Maintainer-email: bengt.lueers@gmail.com
License: UNKNOWN
Platform: UNKNOWN
Classifier: Development Status :: 5 - Production/Stable
Classifier: Environment :: Console
Classifier: Intended Audience :: Science/Research
Classifier: License :: OSI Approved :: GNU Lesser General Public License v2 (LGPLv2)
Classifier: Natural Language :: English
Classifier: Operating System :: OS Independent
Classifier: Programming Language :: Python
Classifier: Programming Language :: Python :: 3
Classifier: Programming Language :: Python :: 3.7
Classifier: Programming Language :: Python :: 3.8
Classifier: Programming Language :: Python :: 3.9
Classifier: Topic :: Scientific/Engineering
Requires-Dist: arrow (>=0.9.0)
